hp3478a_async/__init__.py
hp3478a_async/_version.py
hp3478a_async/enums.py
hp3478a_async/errors.py
hp3478a_async/flags.py
hp3478a_async/hp_3478a.py
hp3478a_async/hp_3478a_helper.py
hp3478a_async-1.4.6.dist-info/licenses/LICENSE
hp3478a_async-1.4.6.dist-info/METADATA
hp3478a_async-1.4.6.dist-info/WHEEL
hp3478a_async-1.4.6.dist-info/top_level.txt
hp3478a_async-1.4.6.dist-info/RECORD
