Metadata-Version: 2.4
Name: hp3478a-async
Version: 1.4.6
Summary: Python3 AsyncIO HP3478A driver
Author-email: Patrick Baus <patrick.baus@physik.tu-darmstadt.de>
License: GNU General Public License v3 (GPLv3)
Project-URL: Homepage, https://github.com/PatrickBaus/pyAsyncHP3478A
Project-URL: Bug Tracker, https://github.com/PatrickBaus/pyAsyncHP3478A/issues
Project-URL: Download, https://github.com/PatrickBaus/pyAsyncHP3478A/releases
Project-URL: Documentation, https://patrickbaus.github.io/pyAsyncHP3478A/
Keywords: HP3478A,GPIB,API
Classifier: Programming Language :: Python :: 3
Classifier: Programming Language :: Python :: 3.8
Classifier: Programming Language :: Python :: 3.9
Classifier: Programming Language :: Python :: 3.10
Classifier: Programming Language :: Python :: 3.11
Classifier: Programming Language :: Python :: 3.12
Classifier: Programming Language :: Python :: 3.13
Classifier: Development Status :: 5 - Production/Stable
Classifier: License :: OSI Approved :: GNU General Public License v3 (GPLv3)
Classifier: Operating System :: OS Independent
Classifier: Intended Audience :: Developers
Classifier: Intended Audience :: Science/Research
Classifier: Natural Language :: English
Classifier: Topic :: Home Automation
Classifier: Topic :: Scientific/Engineering
Requires-Python: >=3.7
License-File: LICENSE
Requires-Dist: typing-extensions; python_version < "3.11"
Provides-Extra: linux-gpib
Requires-Dist: async-gpib; extra == "linux-gpib"
Requires-Dist: gpib-ctypes; extra == "linux-gpib"
Provides-Extra: prologix-gpib
Requires-Dist: prologix-gpib-async; extra == "prologix-gpib"
Provides-Extra: dev
Requires-Dist: aiofiles; extra == "dev"
Requires-Dist: async-gpib; extra == "dev"
Requires-Dist: black; extra == "dev"
Requires-Dist: build; extra == "dev"
Requires-Dist: gpib-ctypes; extra == "dev"
Requires-Dist: isort; extra == "dev"
Requires-Dist: mypy; extra == "dev"
Requires-Dist: pre-commit; extra == "dev"
Requires-Dist: prologix-gpib-async; extra == "dev"
Requires-Dist: pylint; extra == "dev"
Requires-Dist: pytest; extra == "dev"
Requires-Dist: twine; extra == "dev"
Provides-Extra: doc
Requires-Dist: myst-parser; extra == "doc"
Requires-Dist: sphinx; extra == "doc"
Provides-Extra: test
Requires-Dist: mypy; extra == "test"
Requires-Dist: pylint; extra == "test"
Requires-Dist: pytest; extra == "test"
Requires-Dist: aiofiles; extra == "test"
Requires-Dist: gpib-ctypes; extra == "test"
Requires-Dist: prologix-gpib-async; extra == "test"
Requires-Dist: setuptools; extra == "test"
Dynamic: license-file
